examples/__init__.py
examples/measurement_app/__init__.py
examples/measurement_app/experiments/__init__.py
examples/measurement_app/experiments/custom_analysis_plot_options.py
examples/measurement_app/experiments/custom_analysis_result_provider.py
examples/measurement_app/experiments/demo_experiment.py
examples/measurement_app/ui/__init__.py
examples/measurement_app/ui/main_window.py
examples/measurement_app/ui/main_window_view_model.py
tk_lab_automation_kit/__init__.py
tk_lab_automation_kit/core/__init__.py
tk_lab_automation_kit/core/killable_thread.py
tk_lab_automation_kit/core/observable_list.py
tk_lab_automation_kit/experiments/__init__.py
tk_lab_automation_kit/experiments/experiment.py
tk_lab_automation_kit/experiments/experiment_handler.py
tk_lab_automation_kit/user_interface/__init__.py
tk_lab_automation_kit/user_interface/config_parameter.py
tk_lab_automation_kit/user_interface/control_command.py
tk_lab_automation_kit/user_interface/control_panel.py
tk_lab_automation_kit/user_interface/custom_frame.py
tk_lab_automation_kit/user_interface/custom_table.py
tk_lab_automation_kit/user_interface/custom_table_cell.py
tk_lab_automation_kit/user_interface/custom_table_row.py
tk_lab_automation_kit/user_interface/custom_table_source.py
tk_lab_automation_kit/user_interface/device_role.py
tk_lab_automation_kit/user_interface/device_selector.py
tk_lab_automation_kit/user_interface/parameter_table.py
tk_lab_automation_kit/user_interface/plot_control.py
tk_lab_automation_kit/user_interface/plot_data.py
tk_lab_automation_kit-0.0.2.dist-info/LICENSE
tk_lab_automation_kit-0.0.2.dist-info/METADATA
tk_lab_automation_kit-0.0.2.dist-info/WHEEL
tk_lab_automation_kit-0.0.2.dist-info/top_level.txt
tk_lab_automation_kit-0.0.2.dist-info/RECORD
